Metadata-Version: 2.4
Name: fnnx
Version: 0.0.11
Summary: A flexible format to package and deploy any ML model.
Author-email: Oleh Kostromin <oleh@beastbyte.ai>
License-Expression: MIT
Classifier: Programming Language :: Python :: 3
Classifier: Operating System :: OS Independent
Requires-Python: >=3.10
Provides-Extra: core
Requires-Dist: numpy<3.0.0,>=1.0.0; extra == "core"
Requires-Dist: onnxruntime<2.0.0,>=1.0.0; extra == "core"
Provides-Extra: extras
Requires-Dist: pydantic<3.0.0,>=2.0.0; extra == "extras"
Provides-Extra: test
Requires-Dist: jsonschema<5.0.0,>=4.0.0; extra == "test"
Requires-Dist: pydantic<3.0.0,>=2.0.0; extra == "test"
